<?xml version="1.0" encoding="UTF-8"?>
<Tokens version="1.0">
	<File path="docs/source/Tutorials/Battery usage.html">
		
		<Token>
			<TokenIdentifier>//apple_ref/occ/doc/Battery usage</TokenIdentifier>
			<Abstract type="html">As the library samples regularly in the background, there can be a significant impact on battery life of the phone while running the app. A few general heuristics can dramatically reduce battery life. Next to that, the library provides a few specific settings that can also reduce battery life when enabled.</Abstract>
			<DeclaredIn>Battery usage-template.markdown</DeclaredIn>
            
			
			<NodeRef refid="3"/>
		</Token>
		
		
        
        
	</File>
</Tokens>